machina_ratiocinatrix/__init__.py
machina_ratiocinatrix/spawn.py
machina_ratiocinatrix/dashboard/__init__.py
machina_ratiocinatrix/dashboard/controls.py
machina_ratiocinatrix/dashboard/instruments.py
machina_ratiocinatrix/gears/__init__.py
machina_ratiocinatrix/gears/forward_reverse.py
machina_ratiocinatrix/machina/__init__.py
machina_ratiocinatrix/machina/githf.py
machina_ratiocinatrix/machina/machina.yaml
machina_ratiocinatrix/machina/starter.py
machina_ratiocinatrix-0.0.5.dist-info/LICENSE
machina_ratiocinatrix-0.0.5.dist-info/METADATA
machina_ratiocinatrix-0.0.5.dist-info/WHEEL
machina_ratiocinatrix-0.0.5.dist-info/top_level.txt
machina_ratiocinatrix-0.0.5.dist-info/RECORD
