Metadata-Version: 2.1
Name: machina-ratiocinatrix
Version: 0.0.5
Summary: Machina Ratiocinatrix
Author-email: Alexander Fedotov <alex.fedotov@aol.com>
Project-URL: Homepage, https://github.com/machina-ratiocinatrix/machina-ratiocinatrix
Project-URL: Bug Tracker, https://github.com/machina-ratiocinatrix/machina-ratiocinatrix/issues
Keywords: machina-ratiocinatrix,multilogue,conversation,ai
Classifier: Programming Language :: Python :: 3
Classifier: License :: OSI Approved :: MIT License
Classifier: Operating System :: OS Independent
Requires-Python: >=3.10
License-File: LICENSE
Requires-Dist: requests >=2.30.0
Requires-Dist: PyGithub >=2.3.0
Requires-Dist: PyYAML >=6.0.1
Requires-Dist: urllib3 >=2.0.4
Requires-Dist: symposium >=0.2.0
Requires-Dist: grammateus >=0.0.13
Requires-Dist: multilogue >=0.0.14
